rest_sms_gateway/__init__.py
rest_sms_gateway/client.py
rest_sms_gateway/connector.py
rest_sms_gateway/conversation.py
rest_sms_gateway/message.py
rest_sms_gateway-0.5.0.dist-info/LICENSE
rest_sms_gateway-0.5.0.dist-info/METADATA
rest_sms_gateway-0.5.0.dist-info/WHEEL
rest_sms_gateway-0.5.0.dist-info/top_level.txt
rest_sms_gateway-0.5.0.dist-info/RECORD
