Metadata-Version: 2.1
Name: rest-sms-gateway
Version: 0.5.0
Summary: UNKNOWN
Home-page: https://github.com/exageraldo/RestSMSGateway
Author: Geraldo Castro
Author-email: victormatheuscastro@gmail.com
License: LGPLv3
Keywords: python api rest sms gateway
Platform: UNKNOWN
Classifier: Programming Language :: Python :: 3
Classifier: Programming Language :: Python :: 3.6
Classifier: Development Status :: 1 - Planning
Classifier: Topic :: Utilities
Classifier: License :: OSI Approved :: GNU Lesser General Public License v3 (LGPLv3)
Classifier: Operating System :: OS Independent
Requires-Dist: requests (==2.20.0)
